[
  {
    "id": 1,
    "title": "Substrick",
    "description": "Aplicación móvil para gestionar tus suscripciones recurrentes y ahorrar dinero.",
    "image": "/images/project1.jpg",
    "technologies": ["TS", "TailwindCSS", "React Native", "Expo", "Supabase"],
    "liveUrl": "https://substrick.com",
    "repoUrl": ""
  },
  {
    "id": 2,
    "title": "Trato Motor",
    "description": "Marketplace de vehiculos usados para una empresa local. Con dashboard administrativo, para gestionar anuncios y usuarios, leads y citas.",
    "image": "/images/project2.jpg",
    "technologies": ["NextJS", "TailwindCSS","Drizzle", "PostgreSQL", "Docker"],
    "liveUrl": "https://tratomotor.es",
    "repoUrl": ""
  },
  {
    "id": 3,
    "title": "Onrecambio",
    "description": "Marketplace B2B para la compra y venta de repuestos de vehículos.",
    "image": "/images/project3.jpg",
    "technologies": ["NextJS", "TypeScript", "Tailwind", "FastAPI","MySQL", "AWS", "Docker"],
    "liveUrl": "https://onrecambio.com",
    "repoUrl": ""
  }
]
